fcsSchool/__init__.py
fcsSchool-0.0.2.dist-info/METADATA
fcsSchool-0.0.2.dist-info/WHEEL
fcsSchool-0.0.2.dist-info/top_level.txt
fcsSchool-0.0.2.dist-info/RECORD
